{
  "packageId": "3",
  "packageSnapshot": {
    "name": "IVF + ED + SM",
    "description": "For cases where embryos need to be created using donor oocytes.",
    "listedPrice": 46000,
    "currency": "EUR",
    "children": [
      { "id": "pkg3-child-1", "kind": "item", "catalogId": "1" },
      { "id": "pkg3-child-2", "kind": "item", "catalogId": "2" },
      { "id": "pkg3-child-3", "kind": "item", "catalogId": "3" },
      { "id": "pkg3-child-4", "kind": "item", "catalogId": "4" },
      { "id": "pkg3-child-5", "kind": "item", "catalogId": "5" },
      { "id": "pkg3-child-6", "kind": "item", "catalogId": "6" },
      { "id": "pkg3-child-7", "kind": "item", "catalogId": "7" },
      { "id": "pkg3-child-8", "kind": "item", "catalogId": "8" },
      { "id": "pkg3-child-9", "kind": "item", "catalogId": "9" },
      { "id": "pkg3-child-10", "kind": "item", "catalogId": "10" },
      { "id": "pkg3-child-11", "kind": "item", "catalogId": "11" },
      { "id": "pkg3-child-12", "kind": "item", "catalogId": "12" },
      { "id": "pkg3-child-13", "kind": "item", "catalogId": "14" },
      { "id": "pkg3-child-14", "kind": "item", "catalogId": "15" },
      { "id": "pkg3-child-15", "kind": "item", "catalogId": "16" },
      { "id": "pkg3-child-16", "kind": "item", "catalogId": "18" },
      { "id": "pkg3-child-17", "kind": "item", "catalogId": "19" },
      { "id": "pkg3-child-18", "kind": "item", "catalogId": "21" },
      { "id": "pkg3-child-19", "kind": "item", "catalogId": "22" },
      { "id": "pkg3-child-20", "kind": "item", "catalogId": "23" },
      { "id": "pkg3-child-21", "kind": "item", "catalogId": "24" },
      { "id": "pkg3-child-22", "kind": "item", "catalogId": "25" }
    ]
  },
  "milestones": [
    {
      "id": "milestone-1",
      "title": "To start the program",
      "taxPercent": 14,
      "showPackageOverview": true,
      "services": [
        { "id": "milestone-1-share", "kind": "percent", "packageId": "3", "percent": 20, "expectedExpenseRole": "scheduled" },
        { "id": "milestone-1-extra-1", "kind": "custom", "name": "Deposit for transportation of SM", "price": 300 },
        { "id": "milestone-1-extra-2", "kind": "custom", "name": "Deposit for medical expenses of SM", "price": 300 }
      ]
    },
    {
      "id": "milestone-2",
      "title": "Two weeks before embryo transfer",
      "taxPercent": 14,
      "showPackageOverview": false,
      "services": [
        { "id": "milestone-2-share", "kind": "percent", "packageId": "3", "percent": 10, "expectedExpenseRole": "scheduled" },
        { "id": "milestone-2-extra-1", "kind": "custom", "name": "Deposit for transportation of SM", "price": 300 },
        { "id": "milestone-2-extra-2", "kind": "custom", "name": "Deposit for medical expenses of SM", "price": 300 }
      ]
    },
    {
      "id": "milestone-3",
      "title": "After confirmation of pregnancy by ultrasound",
      "taxPercent": 14,
      "showPackageOverview": false,
      "services": [
        { "id": "milestone-3-share", "kind": "percent", "packageId": "3", "percent": 15, "expectedExpenseRole": "scheduled" },
        { "id": "milestone-3-extra-1", "kind": "item", "catalogId": "32" },
        { "id": "milestone-3-extra-2", "kind": "custom", "name": "Deposit for transportation of SM", "price": 300 },
        { "id": "milestone-3-extra-3", "kind": "custom", "name": "Deposit for medical expenses of SM", "price": 300 }
      ]
    },
    {
      "id": "milestone-4",
      "title": "On the 12th week of pregnancy",
      "taxPercent": 14,
      "showPackageOverview": false,
      "services": [
        { "id": "milestone-4-share", "kind": "percent", "packageId": "3", "percent": 20, "expectedExpenseRole": "scheduled" },
        { "id": "milestone-4-extra-1", "kind": "custom", "name": "Deposit for transportation of SM", "price": 300 },
        { "id": "milestone-4-extra-2", "kind": "custom", "name": "Deposit for medical expenses of SM", "price": 300 }
      ]
    },
    {
      "id": "milestone-5",
      "title": "On the 18th week of pregnancy",
      "taxPercent": 14,
      "showPackageOverview": false,
      "services": [
        { "id": "milestone-5-share", "kind": "percent", "packageId": "3", "percent": 20, "expectedExpenseRole": "scheduled" },
        { "id": "milestone-5-extra-1", "kind": "custom", "name": "Deposit for transportation of SM", "price": 300 },
        { "id": "milestone-5-extra-2", "kind": "custom", "name": "Deposit for medical expenses of SM", "price": 300 }
      ]
    },
    {
      "id": "milestone-6",
      "title": "On the 36th week of pregnancy",
      "taxPercent": 14,
      "showPackageOverview": false,
      "services": [
        { "id": "milestone-6-share", "kind": "percent", "packageId": "3", "percent": 15, "expectedExpenseRole": "scheduled" },
        { "id": "milestone-6-extra-1", "kind": "item", "catalogId": "61" },
        { "id": "milestone-6-extra-2", "kind": "item", "catalogId": "62" },
        { "id": "milestone-6-extra-3", "kind": "item", "catalogId": "63" },
        { "id": "milestone-6-extra-4", "kind": "item", "catalogId": "64" },
        {
          "id": "milestone-6-extra-5",
          "kind": "custom",
          "name": "Standard service of the independent lawyer, notary and post until the 6 months after delivery",
          "price": 0,
          "priceLabel": "GIFT"
        }
      ]
    }
  ]
}
